foundationallm_agent_plugins/__init__.py
foundationallm_agent_plugins/tool_plugin_manager.py
foundationallm_agent_plugins/workflow_plugin_manager.py
foundationallm_agent_plugins/_metadata/foundationallm_manifest.json
foundationallm_agent_plugins/tools/__init__.py
foundationallm_agent_plugins/tools/foundationallm_code_interpreter_tool.py
foundationallm_agent_plugins/tools/foundationallm_code_interpreter_tool_input.py
foundationallm_agent_plugins/tools/foundationallm_databricks_tool.py
foundationallm_agent_plugins/tools/foundationallm_file_analysis_tool.py
foundationallm_agent_plugins/tools/foundationallm_knowledge_tool.py
foundationallm_agent_plugins/tools/foundationallm_knowledge_tool_input.py
foundationallm_agent_plugins/tools/foundationallm_kql_tool.py
foundationallm_agent_plugins/tools/foundationallm_nop_tool.py
foundationallm_agent_plugins/tools/foundationallm_sql_tool.py
foundationallm_agent_plugins/workflows/__init__.py
foundationallm_agent_plugins/workflows/foundationallm_function_calling_workflow.py
foundationallm_agent_plugins-0.9.7.post10.dist-info/METADATA
foundationallm_agent_plugins-0.9.7.post10.dist-info/WHEEL
foundationallm_agent_plugins-0.9.7.post10.dist-info/top_level.txt
foundationallm_agent_plugins-0.9.7.post10.dist-info/RECORD
